[
    {
        "Unnamed: 0": 737640,
        "School Year": 2022,
        "District Code": 13,
        "District": "Capital School District",
        "School Code": 648,
        "Organization": "Dover High School",
        "Assessment Name": "SAT School-Day (Spring)",
        "ContentArea": "ELA",
        "Race": "African American",
        "Gender": "Male",
        "Grade": "11th Grade",
        "SpecialDemo": "Non-EL Students",
        "Geography": "All Students",
        "SubGroup": "African American/Male/11th Grade/Non-EL Students",
        "RowStatus": "REPORTED",
        "Tested": 76.0,
        "Proficient": 16.0,
        "PctProficient": 21.05,
        "ScaleScoreAvg": 430.39
    },
    {
        "Unnamed: 0": 153852,
        "School Year": 2018,
        "District Code": 13,
        "District": "Capital School District",
        "School Code": 644,
        "Organization": "Central Middle School",
        "Assessment Name": "Smarter Balanced Summative Assessment",
        "ContentArea": "MATH",
        "Race": "All Students",
        "Gender": "Female",
        "Grade": "8th Grade",
        "SpecialDemo": "All Students",
        "Geography": "All Students",
        "SubGroup": "Female/8th Grade",
        "RowStatus": "REPORTED",
        "Tested": 239.0,
        "Proficient": 90.0,
        "PctProficient": 37.66,
        "ScaleScoreAvg": 2536.15
    },
    {
        "Unnamed: 0": 4109,
        "School Year": 2015,
        "District Code": 13,
        "District": "Capital School District",
        "School Code": 636,
        "Organization": "Booker T. Washington Elementary School",
        "Assessment Name": "Smarter Balanced Summative Assessment",
        "ContentArea": "ELA",
        "Race": "All Students",
        "Gender": "Male",
        "Grade": "4th Grade",
        "SpecialDemo": "All Students",
        "Geography": "All Students",
        "SubGroup": "Male/4th Grade",
        "RowStatus": "REPORTED",
        "Tested": 39.0,
        "Proficient": 21.0,
        "PctProficient": 53.85,
        "ScaleScoreAvg": 2485.44
    },
    {
        "Unnamed: 0": 284599,
        "School Year": 2020,
        "District Code": 13,
        "District": "Capital School District",
        "School Code": 648,
        "Organization": "Dover High School",
        "Assessment Name": "SAT School-Day (Spring)",
        "ContentArea": "ELA",
        "Race": "White",
        "Gender": "Female",
        "Grade": "11th Grade",
        "SpecialDemo": "Non-EL Students",
        "Geography": "All Students",
        "SubGroup": "White/Female/11th Grade/Non-EL Students",
        "RowStatus": "REPORTED",
        "Tested": 60.0,
        "Proficient": 38.0,
        "PctProficient": 63.33,
        "ScaleScoreAvg": 509.5
    },
    {
        "Unnamed: 0": 1019348,
        "School Year": 2023,
        "District Code": 13,
        "District": "Capital School District",
        "School Code": 646,
        "Organization": "William Henry Middle School",
        "Assessment Name": "Smarter Balanced Summative Assessment",
        "ContentArea": "MATH",
        "Race": "All Students",
        "Gender": "Male",
        "Grade": "All Students",
        "SpecialDemo": "All Students",
        "Geography": "All Students",
        "SubGroup": "Male",
        "RowStatus": "REPORTED",
        "Tested": 474.0,
        "Proficient": 56.0,
        "PctProficient": 11.81,
        "ScaleScoreAvg": 2422.8
    },
    {
        "Unnamed: 0": 1324748,
        "School Year": 2024,
        "District Code": 13,
        "District": "Capital School District",
        "School Code": 648,
        "Organization": "Dover High School",
        "Assessment Name": "Delaware System of Student Assessment (DeSSA)",
        "ContentArea": "SOC",
        "Race": "All Students",
        "Gender": "Female",
        "Grade": "All Students",
        "SpecialDemo": "Non-Foster Care",
        "Geography": "All Students",
        "SubGroup": "Female/Non-Foster Care",
        "RowStatus": "REPORTED",
        "Tested": 196.0,
        "Proficient": 33.0,
        "PctProficient": 16.84,
        "ScaleScoreAvg": 569.71
    },
    {
        "Unnamed: 0": 1305383,
        "School Year": 2024,
        "District Code": 13,
        "District": "Capital School District",
        "School Code": 0,
        "Organization": "Capital School District",
        "Assessment Name": "Smarter Balanced Summative Assessment",
        "ContentArea": "MATH",
        "Race": "All Students",
        "Gender": "Male",
        "Grade": "8th Grade",
        "SpecialDemo": "Non-Foster Care",
        "Geography": "All Students",
        "SubGroup": "Male/8th Grade/Non-Foster Care",
        "RowStatus": "REPORTED",
        "Tested": 214.0,
        "Proficient": 16.0,
        "PctProficient": 7.48,
        "ScaleScoreAvg": 2428.71
    },
    {
        "Unnamed: 0": 104937,
        "School Year": 2017,
        "District Code": 13,
        "District": "Capital School District",
        "School Code": 0,
        "Organization": "Capital School District",
        "Assessment Name": "Smarter Balanced Summative Assessment",
        "ContentArea": "MATH",
        "Race": "African American",
        "Gender": "All Students",
        "Grade": "4th Grade",
        "SpecialDemo": "All Students",
        "Geography": "All Students",
        "SubGroup": "African American/4th Grade",
        "RowStatus": "REPORTED",
        "Tested": 240.0,
        "Proficient": 89.0,
        "PctProficient": 37.08,
        "ScaleScoreAvg": 2460.49
    },
    {
        "Unnamed: 0": 1309558,
        "School Year": 2024,
        "District Code": 13,
        "District": "Capital School District",
        "School Code": 633,
        "Organization": "Middle School of Excellence",
        "Assessment Name": "Smarter Balanced Summative Assessment",
        "ContentArea": "MATH",
        "Race": "White",
        "Gender": "Female",
        "Grade": "7th Grade",
        "SpecialDemo": "All Students",
        "Geography": "All Students",
        "SubGroup": "White/Female/7th Grade",
        "RowStatus": "REPORTED",
        "Tested": 19.0,
        "Proficient": 5.0,
        "PctProficient": 26.32,
        "ScaleScoreAvg": 2466.63
    },
    {
        "Unnamed: 0": 3481,
        "School Year": 2015,
        "District Code": 13,
        "District": "Capital School District",
        "School Code": 0,
        "Organization": "Capital School District",
        "Assessment Name": "Smarter Balanced Summative Assessment",
        "ContentArea": "MATH",
        "Race": "Hispanic/Latino",
        "Gender": "All Students",
        "Grade": "3rd Grade",
        "SpecialDemo": "All Students",
        "Geography": "All Students",
        "SubGroup": "Hispanic/Latino/3rd Grade",
        "RowStatus": "REPORTED",
        "Tested": 58.0,
        "Proficient": 28.0,
        "PctProficient": 48.28,
        "ScaleScoreAvg": 2428.0
    }
]