<?xml version="1.0" encoding="utf-8"?>
<clothing-items>
 <clothing>
  <id>
   364766305
  </id>
  <name>
   Fila Gloves K-6998
  </name>
  <category>
   Gloves
  </category>
  <size>
   L
  </size>
  <color>
   Красный
  </color>
  <material>
   Полиэстер
  </material>
  <price>
   256360
  </price>
  <rating>
   1.71
  </rating>
  <reviews>
   567668
  </reviews>
  <new>
   -
  </new>
 </clothing>
 <clothing>
  <id>
   263582381
  </id>
  <name>
   New Balance Jacket C-7814
  </name>
  <category>
   Jacket
  </category>
  <size>
   XL
  </size>
  <color>
   Фиолетовый
  </color>
  <material>
   Полиэстер
  </material>
  <price>
   907106
  </price>
  <rating>
   2.93
  </rating>
  <reviews>
   523725
  </reviews>
  <exclusive>
   no
  </exclusive>
  <sporty>
   no
  </sporty>
 </clothing>
 <clothing>
  <id>
   131656105
  </id>
  <name>
   Puma T-shirt V-6291
  </name>
  <category>
   T-shirt
  </category>
  <size>
   L
  </size>
  <color>
   Оранжевый
  </color>
  <material>
   Лен
  </material>
  <price>
   992851
  </price>
  <rating>
   1.0
  </rating>
  <reviews>
   520401
  </reviews>
  <new>
   -
  </new>
  <sporty>
   no
  </sporty>
 </clothing>
 <clothing>
  <id>
   250315526
  </id>
  <name>
   Lacoste T-shirt F-5018
  </name>
  <category>
   T-shirt
  </category>
  <size>
   L
  </size>
  <color>
   Синий
  </color>
  <material>
   Кожа
  </material>
  <price>
   352106
  </price>
  <rating>
   4.88
  </rating>
  <reviews>
   714962
  </reviews>
  <new>
   -
  </new>
  <exclusive>
   no
  </exclusive>
 </clothing>
 <clothing>
  <id>
   718479162
  </id>
  <name>
   Ellesse Shirt O-1406
  </name>
  <category>
   Shirt
  </category>
  <size>
   XXL
  </size>
  <color>
   Желтый
  </color>
  <material>
   Кожа
  </material>
  <price>
   989740
  </price>
  <rating>
   1.12
  </rating>
  <reviews>
   483672
  </reviews>
  <new>
   -
  </new>
  <exclusive>
   no
  </exclusive>
 </clothing>
 <clothing>
  <id>
   121508728
  </id>
  <name>
   Asics Hat F-8450
  </name>
  <category>
   Hat
  </category>
  <size>
   L
  </size>
  <color>
   Синий
  </color>
  <material>
   Вискоза
  </material>
  <price>
   671051
  </price>
  <rating>
   4.17
  </rating>
  <reviews>
   874016
  </reviews>
  <new>
   -
  </new>
  <exclusive>
   yes
  </exclusive>
  <sporty>
   no
  </sporty>
 </clothing>
 <clothing>
  <id>
   438957433
  </id>
  <name>
   Nike Gloves H-2867
  </name>
  <category>
   Gloves
  </category>
  <size>
   XXL
  </size>
  <color>
   Зеленый
  </color>
  <material>
   Нейлон
  </material>
  <price>
   499455
  </price>
  <rating>
   3.11
  </rating>
  <reviews>
   539607
  </reviews>
  <new>
   +
  </new>
  <exclusive>
   no
  </exclusive>
 </clothing>
 <clothing>
  <id>
   401445347
  </id>
  <name>
   Ellesse Socks A-5531
  </name>
  <category>
   Socks
  </category>
  <size>
   XXL
  </size>
  <color>
   Красный
  </color>
  <material>
   Вискоза
  </material>
  <price>
   229979
  </price>
  <rating>
   1.49
  </rating>
  <reviews>
   715254
  </reviews>
  <new>
   -
  </new>
  <sporty>
   yes
  </sporty>
 </clothing>
 <clothing>
  <id>
   921876853
  </id>
  <name>
   New Balance Jeans A-5906
  </name>
  <category>
   Jeans
  </category>
  <size>
   M
  </size>
  <color>
   Зеленый
  </color>
  <material>
   Нейлон
  </material>
  <price>
   976420
  </price>
  <rating>
   4.46
  </rating>
  <reviews>
   65598
  </reviews>
  <sporty>
   yes
  </sporty>
 </clothing>
 <clothing>
  <id>
   165019143
  </id>
  <name>
   Nike Jeans U-2547
  </name>
  <category>
   Jeans
  </category>
  <size>
   XL
  </size>
  <color>
   Фиолетовый
  </color>
  <material>
   Кожа
  </material>
  <price>
   187888
  </price>
  <rating>
   2.59
  </rating>
  <reviews>
   746020
  </reviews>
  <exclusive>
   yes
  </exclusive>
 </clothing>
 <clothing>
  <id>
   490696462
  </id>
  <name>
   Nike Hat W-1254
  </name>
  <category>
   Hat
  </category>
  <size>
   XXL
  </size>
  <color>
   Оранжевый
  </color>
  <material>
   Кожа
  </material>
  <price>
   931876
  </price>
  <rating>
   2.33
  </rating>
  <reviews>
   633671
  </reviews>
  <new>
   +
  </new>
  <exclusive>
   yes
  </exclusive>
  <sporty>
   no
  </sporty>
 </clothing>
 <clothing>
  <id>
   219241289
  </id>
  <name>
   New Balance Skirt D-6876
  </name>
  <category>
   Skirt
  </category>
  <size>
   XL
  </size>
  <color>
   Оранжевый
  </color>
  <material>
   Вискоза
  </material>
  <price>
   796233
  </price>
  <rating>
   1.49
  </rating>
  <reviews>
   672570
  </reviews>
  <exclusive>
   no
  </exclusive>
 </clothing>
 <clothing>
  <id>
   540347127
  </id>
  <name>
   Asics Socks S-7154
  </name>
  <category>
   Socks
  </category>
  <size>
   S
  </size>
  <color>
   Оранжевый
  </color>
  <material>
   Лен
  </material>
  <price>
   769252
  </price>
  <rating>
   3.09
  </rating>
  <reviews>
   737775
  </reviews>
  <exclusive>
   no
  </exclusive>
 </clothing>
 <clothing>
  <id>
   847317617
  </id>
  <name>
   Addidas Shirt N-2620
  </name>
  <category>
   Shirt
  </category>
  <size>
   M
  </size>
  <color>
   Голубой
  </color>
  <material>
   Вискоза
  </material>
  <price>
   882250
  </price>
  <rating>
   2.2
  </rating>
  <reviews>
   228752
  </reviews>
  <new>
   -
  </new>
 </clothing>
 <clothing>
  <id>
   493959945
  </id>
  <name>
   DC Pants J-4906
  </name>
  <category>
   Pants
  </category>
  <size>
   XL
  </size>
  <color>
   Голубой
  </color>
  <material>
   Лен
  </material>
  <price>
   663126
  </price>
  <rating>
   3.19
  </rating>
  <reviews>
   677652
  </reviews>
  <new>
   +
  </new>
  <sporty>
   no
  </sporty>
 </clothing>
 <clothing>
  <id>
   564258216
  </id>
  <name>
   Vans Gloves X-2062
  </name>
  <category>
   Gloves
  </category>
  <size>
   XXL
  </size>
  <color>
   Красный
  </color>
  <material>
   Кожа
  </material>
  <price>
   166387
  </price>
  <rating>
   4.6
  </rating>
  <reviews>
   788768
  </reviews>
  <new>
   -
  </new>
  <exclusive>
   no
  </exclusive>
 </clothing>
 <clothing>
  <id>
   313565790
  </id>
  <name>
   Nike Jeans U-1511
  </name>
  <category>
   Jeans
  </category>
  <size>
   M
  </size>
  <color>
   Желтый
  </color>
  <material>
   Лен
  </material>
  <price>
   651980
  </price>
  <rating>
   4.44
  </rating>
  <reviews>
   166075
  </reviews>
  <exclusive>
   yes
  </exclusive>
  <sporty>
   no
  </sporty>
 </clothing>
 <clothing>
  <id>
   276017322
  </id>
  <name>
   New Balance Socks Y-1338
  </name>
  <category>
   Socks
  </category>
  <size>
   M
  </size>
  <color>
   Синий
  </color>
  <material>
   Лен
  </material>
  <price>
   320862
  </price>
  <rating>
   2.16
  </rating>
  <reviews>
   719240
  </reviews>
  <new>
   +
  </new>
  <sporty>
   yes
  </sporty>
 </clothing>
 <clothing>
  <id>
   279779958
  </id>
  <name>
   PleinSport Shirt F-9590
  </name>
  <category>
   Shirt
  </category>
  <size>
   S
  </size>
  <color>
   Голубой
  </color>
  <material>
   Шерсть
  </material>
  <price>
   276156
  </price>
  <rating>
   3.81
  </rating>
  <reviews>
   318389
  </reviews>
  <new>
   +
  </new>
  <sporty>
   no
  </sporty>
 </clothing>
 <clothing>
  <id>
   998637146
  </id>
  <name>
   Reebok Skirt W-2105
  </name>
  <category>
   Skirt
  </category>
  <size>
   M
  </size>
  <color>
   Красный
  </color>
  <material>
   Нейлон
  </material>
  <price>
   444287
  </price>
  <rating>
   2.51
  </rating>
  <reviews>
   665146
  </reviews>
  <new>
   +
  </new>
  <sporty>
   yes
  </sporty>
 </clothing>
 <clothing>
  <id>
   107964816
  </id>
  <name>
   Asics Handbags I-3558
  </name>
  <category>
   Handbags
  </category>
  <size>
   L
  </size>
  <color>
   Голубой
  </color>
  <material>
   Шелк
  </material>
  <price>
   632682
  </price>
  <rating>
   4.33
  </rating>
  <reviews>
   242350
  </reviews>
  <sporty>
   no
  </sporty>
 </clothing>
 <clothing>
  <id>
   982075214
  </id>
  <name>
   Vans Blouse K-9098
  </name>
  <category>
   Blouse
  </category>
  <size>
   XL
  </size>
  <color>
   Фиолетовый
  </color>
  <material>
   Шелк
  </material>
  <price>
   497169
  </price>
  <rating>
   4.04
  </rating>
  <reviews>
   961524
  </reviews>
 </clothing>
 <clothing>
  <id>
   749766102
  </id>
  <name>
   Reebok Jeans P-2484
  </name>
  <category>
   Jeans
  </category>
  <size>
   S
  </size>
  <color>
   Голубой
  </color>
  <material>
   Хлопок
  </material>
  <price>
   490641
  </price>
  <rating>
   1.36
  </rating>
  <reviews>
   221630
  </reviews>
  <new>
   -
  </new>
  <exclusive>
   no
  </exclusive>
  <sporty>
   yes
  </sporty>
 </clothing>
 <clothing>
  <id>
   882090155
  </id>
  <name>
   Asics Gloves C-6043
  </name>
  <category>
   Gloves
  </category>
  <size>
   S
  </size>
  <color>
   Зеленый
  </color>
  <material>
   Нейлон
  </material>
  <price>
   864030
  </price>
  <rating>
   3.54
  </rating>
  <reviews>
   850027
  </reviews>
  <exclusive>
   no
  </exclusive>
 </clothing>
 <clothing>
  <id>
   775478566
  </id>
  <name>
   Adidas Skirt F-3570
  </name>
  <category>
   Skirt
  </category>
  <size>
   S
  </size>
  <color>
   Желтый
  </color>
  <material>
   Нейлон
  </material>
  <price>
   453852
  </price>
  <rating>
   2.86
  </rating>
  <reviews>
   23422
  </reviews>
 </clothing>
 <clothing>
  <id>
   486526624
  </id>
  <name>
   New Balance Pants F-2164
  </name>
  <category>
   Pants
  </category>
  <size>
   M
  </size>
  <color>
   Голубой
  </color>
  <material>
   Шерсть
  </material>
  <price>
   860788
  </price>
  <rating>
   2.5
  </rating>
  <reviews>
   582850
  </reviews>
  <new>
   +
  </new>
  <exclusive>
   yes
  </exclusive>
  <sporty>
   yes
  </sporty>
 </clothing>
 <clothing>
  <id>
   168153635
  </id>
  <name>
   Adidas Skirt J-1863
  </name>
  <category>
   Skirt
  </category>
  <size>
   L
  </size>
  <color>
   Зеленый
  </color>
  <material>
   Хлопок
  </material>
  <price>
   553595
  </price>
  <rating>
   1.64
  </rating>
  <reviews>
   197194
  </reviews>
  <new>
   -
  </new>
  <exclusive>
   no
  </exclusive>
  <sporty>
   no
  </sporty>
 </clothing>
 <clothing>
  <id>
   812573235
  </id>
  <name>
   Addidas Blouse P-8876
  </name>
  <category>
   Blouse
  </category>
  <size>
   XXL
  </size>
  <color>
   Оранжевый
  </color>
  <material>
   Кожа
  </material>
  <price>
   916948
  </price>
  <rating>
   1.87
  </rating>
  <reviews>
   495963
  </reviews>
  <new>
   +
  </new>
  <exclusive>
   yes
  </exclusive>
 </clothing>
 <clothing>
  <id>
   249484166
  </id>
  <name>
   Vans T-shirt N-5834
  </name>
  <category>
   T-shirt
  </category>
  <size>
   M
  </size>
  <color>
   Голубой
  </color>
  <material>
   Кожа
  </material>
  <price>
   697433
  </price>
  <rating>
   2.89
  </rating>
  <reviews>
   91168
  </reviews>
  <new>
   +
  </new>
  <exclusive>
   yes
  </exclusive>
 </clothing>
 <clothing>
  <id>
   337777145
  </id>
  <name>
   Brooks T-shirt W-3036
  </name>
  <category>
   T-shirt
  </category>
  <size>
   XXL
  </size>
  <color>
   Синий
  </color>
  <material>
   Вискоза
  </material>
  <price>
   730712
  </price>
  <rating>
   1.97
  </rating>
  <reviews>
   305673
  </reviews>
  <new>
   -
  </new>
  <exclusive>
   no
  </exclusive>
 </clothing>
 <clothing>
  <id>
   902154750
  </id>
  <name>
   Reebok Pants K-5070
  </name>
  <category>
   Pants
  </category>
  <size>
   XXL
  </size>
  <color>
   Синий
  </color>
  <material>
   Шерсть
  </material>
  <price>
   404556
  </price>
  <rating>
   4.61
  </rating>
  <reviews>
   266927
  </reviews>
  <new>
   -
  </new>
 </clothing>
 <clothing>
  <id>
   563065898
  </id>
  <name>
   Under Armour Hat B-9802
  </name>
  <category>
   Hat
  </category>
  <size>
   XXL
  </size>
  <color>
   Синий
  </color>
  <material>
   Хлопок
  </material>
  <price>
   957031
  </price>
  <rating>
   1.91
  </rating>
  <reviews>
   254821
  </reviews>
  <exclusive>
   no
  </exclusive>
 </clothing>
 <clothing>
  <id>
   866670655
  </id>
  <name>
   Ellesse Umbrellas I-1271
  </name>
  <category>
   Umbrellas
  </category>
  <size>
   S
  </size>
  <color>
   Красный
  </color>
  <material>
   Шерсть
  </material>
  <price>
   950439
  </price>
  <rating>
   1.2
  </rating>
  <reviews>
   165775
  </reviews>
  <new>
   +
  </new>
  <exclusive>
   no
  </exclusive>
  <sporty>
   no
  </sporty>
 </clothing>
 <clothing>
  <id>
   272760771
  </id>
  <name>
   Brooks Socks W-8929
  </name>
  <category>
   Socks
  </category>
  <size>
   L
  </size>
  <color>
   Желтый
  </color>
  <material>
   Полиэстер
  </material>
  <price>
   502616
  </price>
  <rating>
   4.28
  </rating>
  <reviews>
   715891
  </reviews>
  <new>
   -
  </new>
  <sporty>
   yes
  </sporty>
 </clothing>
 <clothing>
  <id>
   651554501
  </id>
  <name>
   Nike Socks D-5630
  </name>
  <category>
   Socks
  </category>
  <size>
   XL
  </size>
  <color>
   Синий
  </color>
  <material>
   Хлопок
  </material>
  <price>
   201144
  </price>
  <rating>
   3.26
  </rating>
  <reviews>
   838792
  </reviews>
  <new>
   -
  </new>
  <exclusive>
   yes
  </exclusive>
  <sporty>
   no
  </sporty>
 </clothing>
 <clothing>
  <id>
   511360858
  </id>
  <name>
   Vans Belts P-8115
  </name>
  <category>
   Belts
  </category>
  <size>
   M
  </size>
  <color>
   Оранжевый
  </color>
  <material>
   Шелк
  </material>
  <price>
   935608
  </price>
  <rating>
   2.32
  </rating>
  <reviews>
   472458
  </reviews>
  <exclusive>
   no
  </exclusive>
 </clothing>
 <clothing>
  <id>
   683006242
  </id>
  <name>
   Fila Shoes Z-7337
  </name>
  <category>
   Shoes
  </category>
  <size>
   L
  </size>
  <color>
   Фиолетовый
  </color>
  <material>
   Вискоза
  </material>
  <price>
   529016
  </price>
  <rating>
   4.94
  </rating>
  <reviews>
   480081
  </reviews>
  <exclusive>
   no
  </exclusive>
 </clothing>
 <clothing>
  <id>
   809582540
  </id>
  <name>
   Ellesse Shirt Y-5318
  </name>
  <category>
   Shirt
  </category>
  <size>
   M
  </size>
  <color>
   Голубой
  </color>
  <material>
   Вискоза
  </material>
  <price>
   930968
  </price>
  <rating>
   1.62
  </rating>
  <reviews>
   125800
  </reviews>
  <new>
   -
  </new>
  <exclusive>
   yes
  </exclusive>
 </clothing>
 <clothing>
  <id>
   843529794
  </id>
  <name>
   Asics Jacket V-5908
  </name>
  <category>
   Jacket
  </category>
  <size>
   XXL
  </size>
  <color>
   Фиолетовый
  </color>
  <material>
   Шелк
  </material>
  <price>
   664342
  </price>
  <rating>
   3.33
  </rating>
  <reviews>
   358534
  </reviews>
  <exclusive>
   no
  </exclusive>
 </clothing>
 <clothing>
  <id>
   146949956
  </id>
  <name>
   PleinSport Gloves A-2186
  </name>
  <category>
   Gloves
  </category>
  <size>
   S
  </size>
  <color>
   Желтый
  </color>
  <material>
   Полиэстер
  </material>
  <price>
   841526
  </price>
  <rating>
   3.42
  </rating>
  <reviews>
   291215
  </reviews>
  <exclusive>
   no
  </exclusive>
 </clothing>
 <clothing>
  <id>
   725376902
  </id>
  <name>
   Under Armour Hat P-7862
  </name>
  <category>
   Hat
  </category>
  <size>
   S
  </size>
  <color>
   Желтый
  </color>
  <material>
   Вискоза
  </material>
  <price>
   805250
  </price>
  <rating>
   1.94
  </rating>
  <reviews>
   440828
  </reviews>
  <new>
   -
  </new>
 </clothing>
 <clothing>
  <id>
   831667072
  </id>
  <name>
   Reebok Shirt M-4456
  </name>
  <category>
   Shirt
  </category>
  <size>
   S
  </size>
  <color>
   Красный
  </color>
  <material>
   Вискоза
  </material>
  <price>
   349330
  </price>
  <rating>
   3.06
  </rating>
  <reviews>
   462951
  </reviews>
  <new>
   +
  </new>
  <sporty>
   yes
  </sporty>
 </clothing>
 <clothing>
  <id>
   871673744
  </id>
  <name>
   Reebok T-shirt B-6153
  </name>
  <category>
   T-shirt
  </category>
  <size>
   XXL
  </size>
  <color>
   Голубой
  </color>
  <material>
   Хлопок
  </material>
  <price>
   935715
  </price>
  <rating>
   3.96
  </rating>
  <reviews>
   546950
  </reviews>
  <new>
   -
  </new>
  <exclusive>
   yes
  </exclusive>
 </clothing>
</clothing-items>
